auto_dep_installer/__init__.py
auto_dep_installer/cli.py
auto_dep_installer/installer.py
auto_dep_installer/scanner.py
auto_dep_installer-0.2.dist-info/METADATA
auto_dep_installer-0.2.dist-info/WHEEL
auto_dep_installer-0.2.dist-info/entry_points.txt
auto_dep_installer-0.2.dist-info/top_level.txt
auto_dep_installer-0.2.dist-info/RECORD
