Metadata-Version: 2.4
Name: auto_dep_installer
Version: 0.2
Summary: Automatically install missing dependencies in your Python project
Home-page: https://github.com/Shubham654/auto_dep_installer
Author: Shubham Chambhare
Author-email: shubhamchambhare654@gmail.com
Project-URL: Bug Tracker, https://github.com/Shubham654/auto_dep_installer/issues
Project-URL: Documentation, https://github.com/Shubham654/auto_dep_installer#readme
Keywords: dependency,management,automation,virtual environment,venv
Classifier: Programming Language :: Python :: 3
Classifier: Programming Language :: Python :: 3.6
Classifier: Programming Language :: Python :: 3.7
Classifier: Programming Language :: Python :: 3.8
Classifier: Programming Language :: Python :: 3.9
Classifier: Programming Language :: Python :: 3.10
Classifier: License :: OSI Approved :: MIT License
Classifier: License :: OSI Approved :: Apache Software License
Classifier: Operating System :: OS Independent
Classifier: Development Status :: 4 - Beta
Classifier: Intended Audience :: Developers
Classifier: Topic :: Software Development :: Build Tools
Classifier: Topic :: Software Development :: Libraries :: Python Modules
Requires-Python: >=3.6
Requires-Dist: setuptools
Dynamic: author
Dynamic: author-email
Dynamic: classifier
Dynamic: description
Dynamic: description-content-type
Dynamic: home-page
Dynamic: keywords
Dynamic: project-url
Dynamic: requires-dist
Dynamic: requires-python
Dynamic: summary
